tokens_cli/__init__.py
tokens_cli/cli.py
tokens_cli/tokenizer.py
tokens_cli-0.1.0.dist-info/licenses/LICENSE
tokens_cli-0.1.0.dist-info/METADATA
tokens_cli-0.1.0.dist-info/WHEEL
tokens_cli-0.1.0.dist-info/entry_points.txt
tokens_cli-0.1.0.dist-info/top_level.txt
tokens_cli-0.1.0.dist-info/RECORD
