Metadata-Version: 2.4
Name: tokens-cli
Version: 0.1.0
Summary: Count tokens in text using tiktoken encoders
Author-email: nik <42a11b@nikdav.is>
License: MIT
Project-URL: Homepage, https://github.com/nikdavis/tokens_cli
Project-URL: Repository, https://github.com/nikdavis/tokens_cli.git
Project-URL: Bug Tracker, https://github.com/nikdavis/tokens_cli/issues
Keywords: tokens,tokenizer,tiktoken,openai,llm,cli
Classifier: Development Status :: 4 - Beta
Classifier: Environment :: Console
Classifier: Intended Audience :: Developers
Classifier: License :: OSI Approved :: MIT License
Classifier: Programming Language :: Python :: 3
Classifier: Programming Language :: Python :: 3.12
Classifier: Topic :: Text Processing :: Linguistic
Classifier: Topic :: Utilities
Requires-Python: >=3.12
License-File: LICENSE
Requires-Dist: tiktoken>=0.5.1
Provides-Extra: dev
Requires-Dist: pytest>=7.0.0; extra == "dev"
Dynamic: license-file
